{
  "kind": "collectionType",
  "collectionName": "calories",
  "info": {
    "name": "calorie",
    "description": ""
  },
  "options": {
    "draftAndPublish": false,
    "timestamps": true,
    "increments": true,
    "comment": ""
  },
  "attributes": {
    "customer_id": {
      "type": "integer",
      "required": false
    },
    "goal": {
      "type": "string",
      "required": true
    },
    "physical_activity": {
      "type": "integer",
      "required": true
    },
    "gender": {
      "type": "string",
      "required": true
    },
    "age": {
      "type": "integer",
      "required": true
    },
    "dob": {
      "type": "date",
      "required": true
    },
    "height": {
      "type": "integer",
      "required": true
    },
    "weight": {
      "type": "integer",
      "unique": false,
      "required": true
    },
    "cart_id": {
      "type": "integer",
      "required": false
    },
    "calorie": {
      "type": "biginteger",
      "required": true
    }
  }
}
